frontend/build/Blackbody.jpg
frontend/build/Bluered.jpg
frontend/build/Blues.jpg
frontend/build/Cividis.jpg
frontend/build/Earth.jpg
frontend/build/Electric.jpg
frontend/build/Greens.jpg
frontend/build/Greys.jpg
frontend/build/Hot.jpg
frontend/build/Inferno.jpg
frontend/build/Jet.jpg
frontend/build/Picnic.jpg
frontend/build/Plasma.jpg
frontend/build/Portland.jpg
frontend/build/Rainbow.jpg
frontend/build/RdBu.jpg
frontend/build/Reds.jpg
frontend/build/Viridis.jpg
frontend/build/YlGnBu.jpg
frontend/build/YlOrRd.jpg
frontend/build/asset-manifest.json
frontend/build/bulk_import_example.txt
frontend/build/bulk_import_example.xlsx
frontend/build/favicon.ico
frontend/build/grab-handle2.svg
frontend/build/help_starter.svg
frontend/build/icon2.svg
frontend/build/index.html
frontend/build/logo192.png
frontend/build/logo512.png
frontend/build/manifest.json
frontend/build/robots.txt
frontend/build/static/css/main.352f9b98.css
frontend/build/static/css/main.352f9b98.css.map
frontend/build/static/js/453.c52a45a4.chunk.js
frontend/build/static/js/453.c52a45a4.chunk.js.map
frontend/build/static/js/main.af9930ae.js
frontend/build/static/js/main.af9930ae.js.LICENSE.txt
frontend/build/static/js/main.af9930ae.js.map
frontend/build/subsets.jpg
plotplot/.flaskenv
plotplot/__init__.py
plotplot/anndata_shim.py
plotplot/api_utils.py
plotplot/backend.py
plotplot/db.py
plotplot/gdrive_cloud.py
plotplot/gdrive_download_thread.py
plotplot/globals.py
plotplot/load_and_resume.py
plotplot/load_csv_thread.py
plotplot/login.py
plotplot/plotplot.py
plotplot/plotplot_config.py
plotplot/point_in_polygon.py
plotplot/session_worker.py
plotplot/user.py
plotplot-1.0.8.dist-info/LICENSE
plotplot-1.0.8.dist-info/METADATA
plotplot-1.0.8.dist-info/WHEEL
plotplot-1.0.8.dist-info/entry_points.txt
plotplot-1.0.8.dist-info/RECORD
