Metadata-Version: 2.1
Name: plotplot
Version: 1.0.8
Summary: Drag and drop plotting, data selection, and filtering
Home-page: https://plotplot.org
License: GPL-3.0-or-later
Author: Andrew Barry
Author-email: abarry@gmail.com
Requires-Python: >=3.10
Classifier: License :: OSI Approved :: GNU General Public License v3 (GPLv3)
Classifier: License :: OSI Approved :: GNU General Public License v3 or later (GPLv3+)
Classifier: Operating System :: OS Independent
Classifier: Programming Language :: Python :: 3
Classifier: Programming Language :: Python :: 3.10
Classifier: Programming Language :: Python :: 3.11
Classifier: Programming Language :: Python :: 3.12
Requires-Dist: Flask (>=2.3.3,<3.0)
Requires-Dist: Flask-Login (>=0.6.3)
Requires-Dist: Werkzeug (>=2.3,<3.0)
Requires-Dist: anndata
Requires-Dist: dask (>=2024.5.0)
Requires-Dist: datashader (>=0.16.0)
Requires-Dist: google-api-python-client (>=2.126)
Requires-Dist: google-auth-httplib2 (>=0.2.0)
Requires-Dist: google-auth-oauthlib (>=1.2.0)
Requires-Dist: gunicorn (>=21.2)
Requires-Dist: line_profiler (>=4.1)
Requires-Dist: numba (>=0.59)
Requires-Dist: numpy (>=1.26,<2.0)
Requires-Dist: oauthlib (>=3.2.2)
Requires-Dist: pandas (>=2.1)
Requires-Dist: platformdirs
Requires-Dist: plotly (==5.13.1)
Requires-Dist: polyleven
Requires-Dist: pyOpenSSL (>=24.0)
Requires-Dist: requests (>=2.31)
Requires-Dist: setuptools (>=68)
Requires-Dist: shapely (>=2.0.3)
Requires-Dist: waitress
